google_py_apis/__init__.py
google_py_apis/gmail_api.py
google_py_apis/google_base_api.py
google_py_apis/google_drive_api.py
google_py_apis/params.py
google_py_apis/util.py
google_py_apis-0.1.9.dist-info/LICENSE
google_py_apis-0.1.9.dist-info/METADATA
google_py_apis-0.1.9.dist-info/WHEEL
google_py_apis-0.1.9.dist-info/top_level.txt
google_py_apis-0.1.9.dist-info/RECORD
