Metadata-Version: 2.1
Name: google-py-apis
Version: 0.1.9
Summary: Wrapper on google's REST APIs. As I use them a lot.
Home-page: https://github.com/siddhantkushwaha/GoogleAPIs
Author: Siddhant Kushwaha
Author-email: k16.siddhant@gmail.com
License: UNKNOWN
Platform: UNKNOWN
Classifier: Programming Language :: Python :: 3
Classifier: License :: OSI Approved :: MIT License
Classifier: Operating System :: OS Independent
Requires-Python: >=3.6
License-File: LICENSE
Requires-Dist: google-api-python-client
Requires-Dist: google-auth-httplib2
Requires-Dist: google-auth-oauthlib
Requires-Dist: pycryptodome
